<?xml version="1.0" ?><annotation>
  <folder>person</folder>
  <filename>000105</filename>
  <path>000105.jpg</path>
  <source>
    <database>Unknown</database>
  </source>
  <size>
    <width>1280</width>
    <height>720</height>
    <depth>3</depth>
  </size>
  <segmented>0</segmented>
  <object>
    <name>car</name>
    <pose>Unspecified</pose>
    <truncated>0</truncated>
    <difficult>0</difficult>
    <bndbox>
      <xmin>750</xmin>
      <ymin>483</ymin>
      <xmax>921</xmax>
      <ymax>660</ymax>
    </bndbox>
  </object>
  <object>
    <name>car</name>
    <pose>Unspecified</pose>
    <truncated>0</truncated>
    <difficult>0</difficult>
    <bndbox>
      <xmin>555</xmin>
      <ymin>392</ymin>
      <xmax>668</xmax>
      <ymax>508</ymax>
    </bndbox>
  </object>
  <object>
    <name>car</name>
    <pose>Unspecified</pose>
    <truncated>0</truncated>
    <difficult>0</difficult>
    <bndbox>
      <xmin>762</xmin>
      <ymin>328</ymin>
      <xmax>863</xmax>
      <ymax>412</ymax>
    </bndbox>
  </object>
  <object>
    <name>car</name>
    <pose>Unspecified</pose>
    <truncated>0</truncated>
    <difficult>0</difficult>
    <bndbox>
      <xmin>541</xmin>
      <ymin>273</ymin>
      <xmax>602</xmax>
      <ymax>333</ymax>
    </bndbox>
  </object>
  <object>
    <name>car</name>
    <pose>Unspecified</pose>
    <truncated>0</truncated>
    <difficult>0</difficult>
    <bndbox>
      <xmin>636</xmin>
      <ymin>297</ymin>
      <xmax>715</xmax>
      <ymax>372</ymax>
    </bndbox>
  </object>
  <object>
    <name>car</name>
    <pose>Unspecified</pose>
    <truncated>0</truncated>
    <difficult>0</difficult>
    <bndbox>
      <xmin>652</xmin>
      <ymin>204</ymin>
      <xmax>689</xmax>
      <ymax>250</ymax>
    </bndbox>
  </object>
  <object>
    <name>car</name>
    <pose>Unspecified</pose>
    <truncated>0</truncated>
    <difficult>0</difficult>
    <bndbox>
      <xmin>536</xmin>
      <ymin>226</ymin>
      <xmax>581</xmax>
      <ymax>264</ymax>
    </bndbox>
  </object>
  <object>
    <name>car</name>
    <pose>Unspecified</pose>
    <truncated>0</truncated>
    <difficult>0</difficult>
    <bndbox>
      <xmin>590</xmin>
      <ymin>192</ymin>
      <xmax>643</xmax>
      <ymax>258</ymax>
    </bndbox>
  </object>
  <object>
    <name>car</name>
    <pose>Unspecified</pose>
    <truncated>0</truncated>
    <difficult>0</difficult>
    <bndbox>
      <xmin>222</xmin>
      <ymin>248</ymin>
      <xmax>295</xmax>
      <ymax>303</ymax>
    </bndbox>
  </object>
  <object>
    <name>car</name>
    <pose>Unspecified</pose>
    <truncated>0</truncated>
    <difficult>0</difficult>
    <bndbox>
      <xmin>175</xmin>
      <ymin>402</ymin>
      <xmax>328</xmax>
      <ymax>557</ymax>
    </bndbox>
  </object>
  <object>
    <name>car</name>
    <pose>Unspecified</pose>
    <truncated>0</truncated>
    <difficult>0</difficult>
    <bndbox>
      <xmin>1</xmin>
      <ymin>400</ymin>
      <xmax>104</xmax>
      <ymax>524</ymax>
    </bndbox>
  </object>
  <object>
    <name>car</name>
    <pose>Unspecified</pose>
    <truncated>0</truncated>
    <difficult>0</difficult>
    <bndbox>
      <xmin>321</xmin>
      <ymin>221</ymin>
      <xmax>368</xmax>
      <ymax>251</ymax>
    </bndbox>
  </object>
  <object>
    <name>car</name>
    <pose>Unspecified</pose>
    <truncated>0</truncated>
    <difficult>0</difficult>
    <bndbox>
      <xmin>650</xmin>
      <ymin>259</ymin>
      <xmax>718</xmax>
      <ymax>298</ymax>
    </bndbox>
  </object>
  <object>
    <name>car</name>
    <pose>Unspecified</pose>
    <truncated>0</truncated>
    <difficult>0</difficult>
    <bndbox>
      <xmin>765</xmin>
      <ymin>224</ymin>
      <xmax>815</xmax>
      <ymax>257</ymax>
    </bndbox>
  </object>
  <object>
    <name>car</name>
    <pose>Unspecified</pose>
    <truncated>0</truncated>
    <difficult>0</difficult>
    <bndbox>
      <xmin>721</xmin>
      <ymin>212</ymin>
      <xmax>754</xmax>
      <ymax>228</ymax>
    </bndbox>
  </object>
  <object>
    <name>car</name>
    <pose>Unspecified</pose>
    <truncated>0</truncated>
    <difficult>0</difficult>
    <bndbox>
      <xmin>701</xmin>
      <ymin>194</ymin>
      <xmax>726</xmax>
      <ymax>210</ymax>
    </bndbox>
  </object>
  <object>
    <name>car</name>
    <pose>Unspecified</pose>
    <truncated>0</truncated>
    <difficult>0</difficult>
    <bndbox>
      <xmin>547</xmin>
      <ymin>193</ymin>
      <xmax>569</xmax>
      <ymax>216</ymax>
    </bndbox>
  </object>
  <object>
    <name>car</name>
    <pose>Unspecified</pose>
    <truncated>0</truncated>
    <difficult>0</difficult>
    <bndbox>
      <xmin>575</xmin>
      <ymin>177</ymin>
      <xmax>597</xmax>
      <ymax>194</ymax>
    </bndbox>
  </object>
  <object>
    <name>car</name>
    <pose>Unspecified</pose>
    <truncated>0</truncated>
    <difficult>0</difficult>
    <bndbox>
      <xmin>605</xmin>
      <ymin>179</ymin>
      <xmax>620</xmax>
      <ymax>191</ymax>
    </bndbox>
  </object>
</annotation>