<?xml version="1.0" ?><annotation>
  <folder>person</folder>
  <filename>000797</filename>
  <path>000797.jpg</path>
  <source>
    <database>Unknown</database>
  </source>
  <size>
    <width>1280</width>
    <height>720</height>
    <depth>3</depth>
  </size>
  <segmented>0</segmented>
  <object>
    <name>car</name>
    <pose>Unspecified</pose>
    <truncated>0</truncated>
    <difficult>0</difficult>
    <bndbox>
      <xmin>511</xmin>
      <ymin>290</ymin>
      <xmax>634</xmax>
      <ymax>460</ymax>
    </bndbox>
  </object>
  <object>
    <name>car</name>
    <pose>Unspecified</pose>
    <truncated>0</truncated>
    <difficult>0</difficult>
    <bndbox>
      <xmin>584</xmin>
      <ymin>118</ymin>
      <xmax>651</xmax>
      <ymax>200</ymax>
    </bndbox>
  </object>
  <object>
    <name>car</name>
    <pose>Unspecified</pose>
    <truncated>0</truncated>
    <difficult>0</difficult>
    <bndbox>
      <xmin>488</xmin>
      <ymin>79</ymin>
      <xmax>546</xmax>
      <ymax>128</ymax>
    </bndbox>
  </object>
  <object>
    <name>car</name>
    <pose>Unspecified</pose>
    <truncated>0</truncated>
    <difficult>0</difficult>
    <bndbox>
      <xmin>919</xmin>
      <ymin>150</ymin>
      <xmax>1043</xmax>
      <ymax>231</ymax>
    </bndbox>
  </object>
  <object>
    <name>car</name>
    <pose>Unspecified</pose>
    <truncated>0</truncated>
    <difficult>0</difficult>
    <bndbox>
      <xmin>677</xmin>
      <ymin>72</ymin>
      <xmax>728</xmax>
      <ymax>121</ymax>
    </bndbox>
  </object>
  <object>
    <name>car</name>
    <pose>Unspecified</pose>
    <truncated>0</truncated>
    <difficult>0</difficult>
    <bndbox>
      <xmin>644</xmin>
      <ymin>15</ymin>
      <xmax>692</xmax>
      <ymax>51</ymax>
    </bndbox>
  </object>
  <object>
    <name>car</name>
    <pose>Unspecified</pose>
    <truncated>0</truncated>
    <difficult>0</difficult>
    <bndbox>
      <xmin>752</xmin>
      <ymin>22</ymin>
      <xmax>797</xmax>
      <ymax>50</ymax>
    </bndbox>
  </object>
  <object>
    <name>car</name>
    <pose>Unspecified</pose>
    <truncated>0</truncated>
    <difficult>0</difficult>
    <bndbox>
      <xmin>1230</xmin>
      <ymin>52</ymin>
      <xmax>1280</xmax>
      <ymax>113</ymax>
    </bndbox>
  </object>
</annotation>